grcalendar/__init__.py
grcalendar/grcalendar.py
grcalendar/grcalendar.pyi
grcalendar-0.0.1.dist-info/METADATA
grcalendar-0.0.1.dist-info/WHEEL
grcalendar-0.0.1.dist-info/RECORD
